prestoplot/__init__.py
prestoplot/_version.py
prestoplot/cli.py
prestoplot/contexts.py
prestoplot/db.py
prestoplot/grammars.py
prestoplot/http.py
prestoplot/markov.py
prestoplot/py.typed
prestoplot/seeds.py
prestoplot/storages.py
prestoplot/story.py
prestoplot/texts.py
prestoplot-0.6.1.dist-info/METADATA
prestoplot-0.6.1.dist-info/WHEEL
prestoplot-0.6.1.dist-info/entry_points.txt
prestoplot-0.6.1.dist-info/licenses/AUTHORS
prestoplot-0.6.1.dist-info/licenses/LICENSE
prestoplot-0.6.1.dist-info/RECORD
