Metadata-Version: 2.4
Name: prestoplot
Version: 0.6.1
Summary: Generative grammars for idea generation.
Project-URL: Homepage, https://github.com/eykd/prestoplot
Project-URL: Issues, https://github.com/eykd/prestoplot/issues
Project-URL: Repository, https://github.com/eykd/prestoplot
Author-email: David Eyk <david@eykd.net>
License-Expression: MIT
License-File: AUTHORS
License-File: LICENSE
Classifier: Development Status :: 4 - Beta
Classifier: Environment :: Console
Classifier: Intended Audience :: Developers
Classifier: Intended Audience :: Information Technology
Classifier: License :: OSI Approved :: MIT License
Classifier: Operating System :: OS Independent
Classifier: Programming Language :: Python
Requires-Python: >=3.11
Requires-Dist: click
Requires-Dist: funcy
Requires-Dist: jinja2
Requires-Dist: markdown
Requires-Dist: msgpack
Requires-Dist: pyyaml
